AUTHORS.rst
CONTRIBUTING.rst
HISTORY.rst
LICENSE
MANIFEST.in
README.rst
pyproject.toml
setup.cfg
setup.py
docs/Makefile
docs/authors.rst
docs/conf.py
docs/contributing.rst
docs/history.rst
docs/index.rst
docs/installation.rst
docs/make.bat
docs/modules.rst
docs/phase_curve_tools.rst
docs/readme.rst
docs/usage.rst
phase_curve_tools/__init__.py
phase_curve_tools/bestFit.py
phase_curve_tools/constants.h
phase_curve_tools/hg.c
phase_curve_tools/hg.pyx
phase_curve_tools/hg12.c
phase_curve_tools/hg12.pyx
phase_curve_tools/hg1g2.c
phase_curve_tools/hg1g2.pxd
phase_curve_tools/hg1g2.pyx
phase_curve_tools/reducedMag.c
phase_curve_tools/reducedMag.pyx
phase_curve_tools/useAstroQuery.py
phase_curve_tools/valid_arg.pxd
phase_curve_tools.egg-info/PKG-INFO
phase_curve_tools.egg-info/SOURCES.txt
phase_curve_tools.egg-info/dependency_links.txt
phase_curve_tools.egg-info/not-zip-safe
phase_curve_tools.egg-info/requires.txt
phase_curve_tools.egg-info/top_level.txt
tests/__init__.py
tests/test_phase_curve_tools.py