Metadata-Version: 2.1
Name: phase-curve-tools
Version: 0.4.6
Summary: A Python package for asteroid phase curves
Home-page: https://github.com/drk98/phase_curve_tools
Author: Daniel Kramer
Author-email: drk98@nau.edu
License: MIT license
Keywords: phase_curve_tools
Platform: UNKNOWN
Classifier: Development Status :: 2 - Pre-Alpha
Classifier: Intended Audience :: Developers
Classifier: License :: OSI Approved :: MIT License
Classifier: Natural Language :: English
Classifier: Programming Language :: Python :: 3
Classifier: Programming Language :: Python :: 3.8
Classifier: Programming Language :: Python :: 3.9
Classifier: Programming Language :: Python :: 3.10
Requires-Python: >=3.8
License-File: LICENSE
License-File: AUTHORS.rst
